[
  {
    "id": 1,
    "imageUrl": "src/assets/samplework/samp2.jpg",
    "descriptor": "Crisp Coverage",
    "title": "Interior wall and ceiling painting"
  },
  {
    "id": 2,
    "imageUrl": "src/assets/samplework/samp4.jpg",
    "descriptor": "Focal Feature",
    "title": "Accent walls"
  },
  {
    "id": 3,
    "imageUrl": "src/assets/samplework/samp3.jpg",
    "descriptor": "Weather-Resistant",
    "title": "Exterior siding, brick, stucco, and trim painting"
  },
  {
    "id": 4,
    "imageUrl": "src/assets/samplework/samp1.jpg",
    "descriptor": "Detailed Trim",
    "title": "Crown molding and baseboard painting"
  },
  {
    "id": 5,
    "imageUrl": "src/assets/samplework/samp1.jpg",
    "descriptor": "Refined Finish",
    "title": "Cabinet painting and staining"
  },
  {
    "id": 6,
    "imageUrl": "src/assets/samplework/samp1.jpg",
    "descriptor": "Refresh Touch",
    "title": "Recoat windows and door frames"
  },
  {
    "id": 7,
    "imageUrl": "src/assets/samplework/samp1.jpg",
    "descriptor": "Exterior Revamp",
    "title": "Brick homes painting and color refreshes"
  }
]
